ailingues_core/__init__.py
ailingues_core/__init__.pyi
ailingues_core/py.typed
ailingues_core/network/__init__.py
ailingues_core/network/__init__.pyi
ailingues_core/network/requests.cpython-311-x86_64-linux-gnu.so
ailingues_core/network/requests.pyi
ailingues_core/network/upload.cpython-311-x86_64-linux-gnu.so
ailingues_core/network/upload.pyi
ailingues_core/network/search/__init__.py
ailingues_core/network/search/__init__.pyi
ailingues_core/network/search/duckduckgo.cpython-311-x86_64-linux-gnu.so
ailingues_core/network/search/duckduckgo.pyi
ailingues_core/network/search/engine.cpython-311-x86_64-linux-gnu.so
ailingues_core/network/search/engine.pyi
ailingues_core/security/__init__.py
ailingues_core/security/aesgcmbox.cpython-311-x86_64-linux-gnu.so
ailingues_core/security/aesgcmbox.pyi
ailingues_core/security/base64s.cpython-311-x86_64-linux-gnu.so
ailingues_core/security/base64s.pyi
ailingues_core/security/cryptographys.cpython-311-x86_64-linux-gnu.so
ailingues_core/security/cryptographys.pyi
ailingues_core/security/fingerprints.cpython-311-x86_64-linux-gnu.so
ailingues_core/security/fingerprints.pyi
ailingues_core/security/md5s.cpython-311-x86_64-linux-gnu.so
ailingues_core/security/md5s.pyi
ailingues_core/system/__init__.py
ailingues_core/system/__init__.pyi
ailingues_core/system/common.cpython-311-x86_64-linux-gnu.so
ailingues_core/system/common.pyi
ailingues_core/system/cpu.cpython-311-x86_64-linux-gnu.so
ailingues_core/system/cpu.pyi
ailingues_core/system/inspector.cpython-311-x86_64-linux-gnu.so
ailingues_core/system/inspector.pyi
ailingues_core/system/mainboard.cpython-311-x86_64-linux-gnu.so
ailingues_core/system/mainboard.pyi
ailingues_core/system/monitors.cpython-311-x86_64-linux-gnu.so
ailingues_core/system/monitors.pyi
ailingues_core/system/netadapter.cpython-311-x86_64-linux-gnu.so
ailingues_core/system/netadapter.pyi
ailingues_core/system/osinfo.cpython-311-x86_64-linux-gnu.so
ailingues_core-0.3.3.dist-info/METADATA
ailingues_core-0.3.3.dist-info/WHEEL
ailingues_core-0.3.3.dist-info/top_level.txt
ailingues_core-0.3.3.dist-info/RECORD
