Metadata-Version: 2.4
Name: ailingues-core
Version: 0.3.3
Summary: A collection of reusable python core library from AI Lingues.
Author-email: AI Lingues <support@ailingues.com>
License: MIT
Keywords: AILingues,components,core,library
Classifier: Programming Language :: Python :: 3
Classifier: License :: OSI Approved :: MIT License
Classifier: Operating System :: OS Independent
Classifier: Intended Audience :: Developers
Classifier: Topic :: Software Development :: Libraries :: Python Modules
Requires-Python: >=3.11
Requires-Dist: aiohappyeyeballs~=2.6.1
Requires-Dist: aiohttp~=3.12.15
Requires-Dist: aiosignal~=1.4.0
Requires-Dist: annotated-types~=0.7.0
Requires-Dist: async-timeout~=5.0.1
Requires-Dist: attrs~=25.3.0
Requires-Dist: backports.tarfile~=1.2.0
Requires-Dist: build~=1.3.0
Requires-Dist: certifi~=2025.8.3
Requires-Dist: cffi~=1.17.1
Requires-Dist: charset-normalizer~=3.4.2
Requires-Dist: click~=8.2.1
Requires-Dist: colorama~=0.4.6
Requires-Dist: cssselect~=1.3.0
Requires-Dist: cryptography~=45.0.6
Requires-Dist: Cython~=3.1.2
Requires-Dist: ddgs~=9.5.2
Requires-Dist: docutils~=0.22
Requires-Dist: feedfinder2~=0.0.4
Requires-Dist: feedparser~=6.0.11
Requires-Dist: filelock~=3.18.0
Requires-Dist: frozenlist~=1.7.0
Requires-Dist: id~=1.5.0
Requires-Dist: idna~=3.10
Requires-Dist: importlib_metadata~=8.7.0
Requires-Dist: jaraco.classes~=3.4.0
Requires-Dist: jaraco.context~=6.0.1
Requires-Dist: jaraco.functools~=4.2.1
Requires-Dist: joblib~=1.5.1
Requires-Dist: keyring~=25.6.0
Requires-Dist: lxml~=6.0.0
Requires-Dist: lxml_html_clean~=0.4.2
Requires-Dist: markdown-it-py~=3.0.0
Requires-Dist: mdurl~=0.1.2
Requires-Dist: more-itertools~=10.7.0
Requires-Dist: multidict~=6.6.3
Requires-Dist: packaging~=25.0
Requires-Dist: primp~=0.15.0
Requires-Dist: propcache~=0.3.2
Requires-Dist: psutil~=7.0.0
Requires-Dist: py-cpuinfo~=9.0.0
Requires-Dist: pycparser==2.22
Requires-Dist: pydantic~=2.11.7
Requires-Dist: pydantic_core~=2.33.2
Requires-Dist: Pygments~=2.19.2
Requires-Dist: pyproject_hooks~=1.2.0
Requires-Dist: python-dateutil~=2.9.0.post0
Requires-Dist: pywin32-ctypes~=0.2.3
Requires-Dist: PyYAML~=6.0.2
Requires-Dist: readme_renderer~=44.0
Requires-Dist: regex~=2025.7.34
Requires-Dist: requests~=2.32.4
Requires-Dist: requests-file~=2.1.0
Requires-Dist: requests-toolbelt~=1.0.0
Requires-Dist: rfc3986~=2.0.0
Requires-Dist: rich~=14.1.0
Requires-Dist: six~=1.17.0
Requires-Dist: tldextract~=5.3.0
Requires-Dist: tqdm~=4.67.1
Requires-Dist: twine~=6.1.0
Requires-Dist: typing-inspection~=0.4.1
Requires-Dist: typing_extensions~=4.14.1
Requires-Dist: urllib3~=2.5.0
Requires-Dist: yarl~=1.20.1
Requires-Dist: zipp~=3.23.0
